{
  "circuit_number": 8,
  "circuit_name": "8th Judicial Circuit",
  "counties": ["Alachua", "Baker", "Bradford", "Gilchrist", "Levy", "Union"],
  "coordinator": "",
  "department": "Alternative Dispute Resolution (ADR) Department",
  "phone": "(352) 491-4417",
  "email": "",
  "fax": "(352) 381-0109",
  "address": "Alachua County Family/Civil Justice Center, 201 East University Avenue, Gainesville, FL 32601",
  "mailing_address": "",
  "website": "https://circuit8.org/departments-services/mediation/",
  "programs": ["Family", "County civil", "Small claims", "Dependency", "Non-binding arbitration"],
  "county_contacts": [],
  "additional_staff": [],
  "notes": "ADR director name not published. Outer counties use contract mediators. Free small claims mediation at pretrial conferences in Alachua, Baker, Bradford, Levy, and Union Counties. No fee for eviction cases.",
  "hours": "",
  "last_verified": "2026-02-01"
}
